pytest_fluent/__init__.py
pytest_fluent/additional_information.py
pytest_fluent/content_patcher.py
pytest_fluent/event.py
pytest_fluent/importlib_utils.py
pytest_fluent/plugin.py
pytest_fluent/setting_file_loader_action.py
pytest_fluent/test_report.py
pytest_fluent/data/default.stage.json
pytest_fluent/data/schema.stage.json
pytest_fluent-0.4.1.dist-info/LICENSE
pytest_fluent-0.4.1.dist-info/METADATA
pytest_fluent-0.4.1.dist-info/WHEEL
pytest_fluent-0.4.1.dist-info/entry_points.txt
pytest_fluent-0.4.1.dist-info/top_level.txt
pytest_fluent-0.4.1.dist-info/RECORD
