Metadata-Version: 2.1
Name: pytest-fluent
Version: 0.4.1
Summary: A pytest plugin in order to provide logs via fluentd
Author-email: "Rohde & Schwarz GmbH & Co. KG" <info@rohde-schwarz.com>
Maintainer-email: Carsten Sauerbrey <carsten.sauerbrey@rohde-schwarz.com>, Nicola Lambiase <nicola.lambiase@rohde-schwarz.com>
License: MIT
Project-URL: project, https://github.com/Rohde-Schwarz/pytest-fluent
Keywords: pytest,logging,fluent
Platform: Unix
Platform: Linux
Platform: Windows
Classifier: Development Status :: 4 - Beta
Classifier: Intended Audience :: Developers
Classifier: Intended Audience :: Science/Research
Classifier: License :: OSI Approved :: MIT License
Classifier: Operating System :: Microsoft :: Windows
Classifier: Operating System :: POSIX :: Linux
Classifier: Operating System :: MacOS :: MacOS X
Classifier: Programming Language :: Python
Classifier: Topic :: Scientific/Engineering :: Interface Engine/Protocol Translator
Classifier: Topic :: Software Development :: Libraries :: Python Modules
Classifier: Programming Language :: Python :: 3.8
Classifier: Programming Language :: Python :: 3.9
Classifier: Programming Language :: Python :: 3.10
Classifier: Programming Language :: Python :: 3.11
Classifier: Programming Language :: Python :: 3.12
Classifier: Framework :: Pytest
Requires-Python: >=3.8
License-File: LICENSE
Requires-Dist: pytest>=7.0.0
Requires-Dist: msgpack
Requires-Dist: six
Requires-Dist: fluent-logger
Requires-Dist: jsonschema
Requires-Dist: ruamel.yaml
Provides-Extra: docs
Requires-Dist: sphinx; extra == "docs"
Requires-Dist: sphinx-rtd-theme; extra == "docs"
Requires-Dist: myst-parser; extra == "docs"
Provides-Extra: test
Requires-Dist: pytest; extra == "test"
Requires-Dist: coverage[toml]; extra == "test"
Requires-Dist: pytest-cov; extra == "test"
Requires-Dist: pytest-xdist[psutil]; extra == "test"
Requires-Dist: six; extra == "test"
Requires-Dist: importlib-resources; python_version <= "3.8" and extra == "test"
